django_redis/__init__.py
django_redis/cache.py
django_redis/exceptions.py
django_redis/hash_ring.py
django_redis/pool.py
django_redis/util.py
django_redis/client/__init__.py
django_redis/client/default.py
django_redis/client/herd.py
django_redis/client/sentinel.py
django_redis/client/sharded.py
django_redis/compressors/__init__.py
django_redis/compressors/base.py
django_redis/compressors/identity.py
django_redis/compressors/lz4.py
django_redis/compressors/lzma.py
django_redis/compressors/zlib.py
django_redis/compressors/zstd.py
django_redis/serializers/__init__.py
django_redis/serializers/base.py
django_redis/serializers/json.py
django_redis/serializers/msgpack.py
django_redis/serializers/pickle.py
django_redis-5.4.0.dist-info/AUTHORS.rst
django_redis-5.4.0.dist-info/LICENSE
django_redis-5.4.0.dist-info/METADATA
django_redis-5.4.0.dist-info/WHEEL
django_redis-5.4.0.dist-info/top_level.txt
django_redis-5.4.0.dist-info/RECORD
